<?xml version="1.0" encoding="utf-8" ?><dwsync><file name="EventData.php" server="www.blackloyalist.info/public_html/" local="3332456354" remote="11922390932" /><file name="BirchtownMusterData.php" server="www.blackloyalist.info/public_html/" local="3332654027" remote="11922588572" /><file name="BONData.php" server="www.blackloyalist.info/public_html/" local="3332456412" remote="11922390992" /><file name="SecondBirchtownMusterData.php" server="www.blackloyalist.info/public_html/" local="3332456378" remote="11922390932" /><file name="TithablesData.php" server="www.blackloyalist.info/public_html/" local="3332451138" remote="11922390932" /><file name="BirchtownMusterImporter.php" server="www.blackloyalist.info/public_html/" local="3332226069" remote="11922390212" /><file name="BirchtownMusterData.php" server="blackloyalist.info/www/" local="3356560140" remote="20536429324" /><file name="BirchtownMusterImporter.php" server="blackloyalist.info/www/" local="3356560140" remote="20536429324" /><file name="BONData.php" server="blackloyalist.info/www/" local="3373073652" remote="16257975588" /><file name="EventData.php" server="blackloyalist.info/www/" local="3356560140" remote="20536429324" /><file name="SecondBirchtownMusterData.php" server="blackloyalist.info/www/" local="3356560140" remote="20536429324" /><file name="TithablesData.php" server="blackloyalist.info/www/" local="3356560140" remote="20536429324" /><file name="CustomEvent.php" server="blackloyalist.info/www/" local="3356560140" remote="20536429324" /><file name=".tmp_BONData.php.54056~" server="blackloyalist.info/www/" local="3356560140" remote="20536429324" /><file name=".tmp_BONData.php.58449~" server="blackloyalist.info/www/" local="3356560140" remote="20536429324" /><file name=".tmp_BONData.php.97331~" server="blackloyalist.info/www/" local="3356560140" remote="20536429324" /><file name=".tmp_EventData.php.54569~" server="blackloyalist.info/www/" local="3347925480" remote="20527794664" /><file name="RanEvent.php" server="blackloyalist.info/www/" local="3356560140" remote="20536429324" /><file name=".DS_Store" server="blackloyalist.info/www/" local="3334226400" remote="20514095584" /><file name=".tmp_BONData.php.63246~" server="blackloyalist.info/www/" local="3350956620" remote="20530825804" /><file name=".tmp_BONData.php.66102~" server="blackloyalist.info/www/" local="3351117840" remote="20530987024" /><file name=".tmp_BirchtownMusterData.php.81916~" server="blackloyalist.info/www/" local="3351117840" remote="20530987024" /><file name=".tmp_BirchtownMusterData.php.83713~" server="blackloyalist.info/www/" local="3350956620" remote="20530825804" /><file name="LoyalistClaims.php" server="blackloyalist.info/www/" local="3362433502" remote="16247335428" /><file name="ListSierraLeone.php" server="blackloyalist.info/www/" local="3367221866" remote="16252168968" /><file name="ListSierraLeoneImporter.php" server="blackloyalist.info/www/" local="3367267497" remote="16252169388" /></dwsync>